algo/__init__.py
algo/_version.py
algo/HI/HI.cpython-311-x86_64-linux-gnu.so
algo/HI/__init__.py
algo/RUL/RUL.cpython-311-x86_64-linux-gnu.so
algo/RUL/__init__.py
test_code/HI_Verify.py
test_code/health_index_robot.py
phm_algo_ias-1.3.5.dist-info/METADATA
phm_algo_ias-1.3.5.dist-info/WHEEL
phm_algo_ias-1.3.5.dist-info/top_level.txt
phm_algo_ias-1.3.5.dist-info/RECORD
