Metadata-Version: 2.4
Name: phm-algo-ias
Version: 1.3.5
Summary: Example algo package with Cython-compiled submodules
Author: Your Name
Classifier: Programming Language :: Python :: 3
Classifier: Programming Language :: Cython
Classifier: Programming Language :: C
Requires-Python: >=3.11
Requires-Dist: passlib==1.7.4
Requires-Dist: pandas==2.2.3
Requires-Dist: numpy==2.0.1
Requires-Dist: scipy==1.14.0
Requires-Dist: scikit-learn==1.5.1
Requires-Dist: matplotlib==3.9.2
Requires-Dist: seaborn==0.13.2
Requires-Dist: openpyxl==3.1.5
Requires-Dist: statsmodels==0.14.4
